LICENSE
README.md
setup.cfg
setup.py
src/eaxml2code/__init__.py
src/eaxml2code/__main__.py
src/eaxml2code/main.py
src/eaxml2code/modelbuilder.py
src/eaxml2code/xmlprocessor.py
src/eaxml2code.egg-info/PKG-INFO
src/eaxml2code.egg-info/SOURCES.txt
src/eaxml2code.egg-info/dependency_links.txt
src/eaxml2code.egg-info/entry_points.txt
src/eaxml2code.egg-info/requires.txt
src/eaxml2code.egg-info/top_level.txt