Metadata-Version: 2.1
Name: eaxml2code
Version: 0.11
Summary: Generate C headers from SW component design in Enterprise Architect XMI file.
Home-page: https://github.com/cimplart/eaxml2code
Author: CimplArt
Author-email: artwisz@gmail.com
License: Apache License, Version 2.0
Keywords: Enterprise Architect,code generation
Platform: UNKNOWN
Classifier: License :: OSI Approved :: Apache Software License
Classifier: Programming Language :: Python :: 3
Classifier: Intended Audience :: Developers
Classifier: Operating System :: OS Independent
Requires-Python: <3.11,>3.6
License-File: LICENSE
